temprc/__init__.py
temprc-0.1.0.dist-info/entry_points.txt
temprc-0.1.0.dist-info/WHEEL
temprc-0.1.0.dist-info/METADATA
temprc-0.1.0.dist-info/RECORD
