Metadata-Version: 2.1
Name: temprc
Version: 0.1.0
Summary: 
Home-page: https://github.com/
License: MIT
Keywords: vscode,poetry
Author: subbarayudu
Author-email: subbarayudu@micropyramid.com
Requires-Python: >=3.6,<4.0
Classifier: License :: OSI Approved :: MIT License
Classifier: Programming Language :: Python :: 3
Classifier: Programming Language :: Python :: 3.10
Classifier: Programming Language :: Python :: 3.6
Classifier: Programming Language :: Python :: 3.7
Classifier: Programming Language :: Python :: 3.8
Classifier: Programming Language :: Python :: 3.9
Requires-Dist: poetry (>=1.1.11,<2.0.0)
Project-URL: Repository, https://github.com/
